{
	"archive" : {},
	"artifacts" : 
	[
		{
			"path" : "extern/glad/libglad.a"
		}
	],
	"backtrace" : 1,
	"backtraceGraph" : 
	{
		"commands" : 
		[
			"add_library",
			"target_include_directories"
		],
		"files" : 
		[
			"extern/glad/CMakeLists.txt"
		],
		"nodes" : 
		[
			{
				"file" : 0
			},
			{
				"command" : 0,
				"file" : 0,
				"line" : 3,
				"parent" : 0
			},
			{
				"command" : 1,
				"file" : 0,
				"line" : 4,
				"parent" : 0
			}
		]
	},
	"compileGroups" : 
	[
		{
			"compileCommandFragments" : 
			[
				{
					"fragment" : "-g"
				}
			],
			"includes" : 
			[
				{
					"backtrace" : 2,
					"path" : "D:/Coisas/Uni/3Ano2Semestre/CG/lab1/extern/glad/include"
				}
			],
			"language" : "C",
			"sourceIndexes" : 
			[
				1
			]
		}
	],
	"id" : "glad::@6d81f930c6bec73dde7b",
	"name" : "glad",
	"nameOnDisk" : "libglad.a",
	"paths" : 
	{
		"build" : "extern/glad",
		"source" : "extern/glad"
	},
	"sourceGroups" : 
	[
		{
			"name" : "Header Files",
			"sourceIndexes" : 
			[
				0
			]
		},
		{
			"name" : "Source Files",
			"sourceIndexes" : 
			[
				1
			]
		}
	],
	"sources" : 
	[
		{
			"backtrace" : 1,
			"path" : "extern/glad/include/glad/glad.h",
			"sourceGroupIndex" : 0
		},
		{
			"backtrace" : 1,
			"compileGroupIndex" : 0,
			"path" : "extern/glad/src/glad.c",
			"sourceGroupIndex" : 1
		}
	],
	"type" : "STATIC_LIBRARY"
}
